[
  {
    "_id": "toy16",
    "name": "Talking Doll",
    "imgUrl": "https://robohash.org/Talking%20Doll?set=set4&size=200x200",
    "price": 120,
    "labels": [
      "Baby"
    ],
    "createdAt": 1633551029714,
    "inStock": false,
    "creator": {
      "_id": "user2",
      "fullname": "Shimi M"
    }
  },
  {
    "_id": "toy17",
    "name": "Remote Control Car",
    "imgUrl": "https://robohash.org/Remote%20Control%20Car?set=set4&size=200x200",
    "price": 139,
    "labels": [
      "Action Figure",
      "Doll",
      "Pretend Play"
    ],
    "createdAt": 1685743487754,
    "inStock": true,
    "creator": {
      "_id": "user1",
      "fullname": "Puki Ja"
    }
  },
  {
    "_id": "toy29",
    "name": "Action Hero Figure",
    "imgUrl": "https://robohash.org/Action%20Hero%20Figure?set=set4&size=200x200",
    "price": 100,
    "labels": [
      "Doll",
      "Pretend Play"
    ],
    "createdAt": 1763795047448,
    "inStock": false,
    "creator": {
      "_id": "user3",
      "fullname": "Dana Lev"
    }
  },
  {
    "_id": "toy30",
    "name": "Musical Xylophone",
    "imgUrl": "https://robohash.org/Musical%20Xylophone?set=set4&size=200x200",
    "price": 66,
    "labels": [
      "Doll",
      "Electronic"
    ],
    "createdAt": 1744014524987,
    "inStock": false,
    "creator": {
      "_id": "user3",
      "fullname": "Dana Lev"
    }
  }
]